<?xml version="1.0" encoding="UTF-8"?>
<Settings>
	<!-- internal behavior -->
	<Settings Name="com.vector.cfg.model.services.bswintbehavior.synchronization.Settings">
		<Settings Name="ModuleList">
			<Settings Name="Sent_30_Icu">
				<XmlSetting Name="Xml"><![CDATA[
          <Synchronization>
            <BswImplementationName>/MICROSAR/Sent_30_Icu_Impl</BswImplementationName>
            <ModuleName>Sent_30_Icu</ModuleName>
            <ExclusiveAreas>
              <ExclusiveArea name="SENT_30_ICU_EXCLUSIVE_AREA_0"/>
            </ExclusiveAreas>
            <TimingEvents>
            </TimingEvents>
          </Synchronization>
        ]]></XmlSetting>
			</Settings>
		</Settings>
	</Settings>
</Settings>
